<?xml version="1.0"?>
<PlayList xmlns:xsi="http://www.w3.org/2001/XMLSchema-instance" xmlns:xsd="http://www.w3.org/2001/XMLSchema">
  <Playlist>
    <Song>
      <Id>0</Id>
      <Name>ypfsmxfqus</Name>
      <Duration>1.7156445159184024</Duration>
    </Song>
    <Song>
      <Id>1</Id>
      <Name>ujuxluwamkjbfppjqlm</Name>
      <Duration>3.188769495668248</Duration>
    </Song>
    <Song>
      <Id>2</Id>
      <Name>wgohciovfgwvghwwmw</Name>
      <Duration>3.0405408633130326</Duration>
    </Song>
    <Song>
      <Id>3</Id>
      <Name>furhiogdhoeuxlo</Name>
      <Duration>2.1351300185244204</Duration>
    </Song>
    <Song>
      <Id>4</Id>
      <Name>nkpfddiiimsxoadjr</Name>
      <Duration>2.8762825149466669</Duration>
    </Song>
    <Song>
      <Id>5</Id>
      <Name>stiswqsbiu</Name>
      <Duration>2.5280554827898998</Duration>
    </Song>
    <Song>
      <Id>6</Id>
      <Name>fxpwyrnxagtki</Name>
      <Duration>4.1278534215539011</Duration>
    </Song>
    <Song>
      <Id>7</Id>
      <Name>ntemcytbvhljhymd</Name>
      <Duration>1.5982809116124552</Duration>
    </Song>
    <Song>
      <Id>8</Id>
      <Name>cnlrrhbsnohnr</Name>
      <Duration>3.3961104854923256</Duration>
    </Song>
    <Song>
      <Id>9</Id>
      <Name>aebgfenargeqaspes</Name>
      <Duration>3.0445559313728268</Duration>
    </Song>
    <Song>
      <Id>10</Id>
      <Name>cclebfgmost</Name>
      <Duration>4.8845024806840822</Duration>
    </Song>
    <Song>
      <Id>11</Id>
      <Name>lyeidwykyldj</Name>
      <Duration>3.7825392194942289</Duration>
    </Song>
    <Song>
      <Id>12</Id>
      <Name>dubogrxrweyxblxmjtu</Name>
      <Duration>2.6384930995472207</Duration>
    </Song>
    <Song>
      <Id>13</Id>
      <Name>jlddqcaaqnlnkxrfpmn</Name>
      <Duration>2.2993055043273167</Duration>
    </Song>
    <Song>
      <Id>14</Id>
      <Name>dyxxbytowmi</Name>
      <Duration>1.421280344213024</Duration>
    </Song>
    <Song>
      <Id>15</Id>
      <Name>kdaurvmllmbatee</Name>
      <Duration>2.7378196831503043</Duration>
    </Song>
    <Song>
      <Id>16</Id>
      <Name>rfieerbbfcpye</Name>
      <Duration>2.5153287497886123</Duration>
    </Song>
    <Song>
      <Id>17</Id>
      <Name>tllsokqqmkw</Name>
      <Duration>1.1871988187484437</Duration>
    </Song>
    <Song>
      <Id>18</Id>
      <Name>kotxlfggyisqpkvm</Name>
      <Duration>2.7988118356088232</Duration>
    </Song>
    <Song>
      <Id>19</Id>
      <Name>qjrvaugnqqsuav</Name>
      <Duration>3.6841554519180932</Duration>
    </Song>
    <Song>
      <Id>20</Id>
      <Name>ffthvmmdyx</Name>
      <Duration>4.24459980113646</Duration>
    </Song>
    <Song>
      <Id>21</Id>
      <Name>acconfrrsdeqopfmst</Name>
      <Duration>1.7330232494198825</Duration>
    </Song>
    <Song>
      <Id>22</Id>
      <Name>hcaetvesavlhvqpsl</Name>
      <Duration>2.406922048147266</Duration>
    </Song>
    <Song>
      <Id>23</Id>
      <Name>ilcpqhwhpfdtmaracjs</Name>
      <Duration>2.524511304928228</Duration>
    </Song>
    <Song>
      <Id>24</Id>
      <Name>sgrisxpthkoskvajmmx</Name>
      <Duration>4.1119865691810782</Duration>
    </Song>
    <Song>
      <Id>25</Id>
      <Name>sruuyopbpbljruwin</Name>
      <Duration>4.6884115304278264</Duration>
    </Song>
    <Song>
      <Id>26</Id>
      <Name>xrespuarwfkpvxnanw</Name>
      <Duration>4.0088009284850212</Duration>
    </Song>
    <Song>
      <Id>27</Id>
      <Name>gunhademeyy</Name>
      <Duration>1.2629821706856519</Duration>
    </Song>
    <Song>
      <Id>28</Id>
      <Name>ambfdoxejpuntgvupy</Name>
      <Duration>3.7081099886950617</Duration>
    </Song>
    <Song>
      <Id>29</Id>
      <Name>vploquergkkobnmm</Name>
      <Duration>3.8611388564394504</Duration>
    </Song>
    <Song>
      <Id>30</Id>
      <Name>eblwmmjxqiiann</Name>
      <Duration>1.1416207613151617</Duration>
    </Song>
    <Song>
      <Id>31</Id>
      <Name>oplstldfjxrsiixcfm</Name>
      <Duration>3.4199692501779504</Duration>
    </Song>
    <Song>
      <Id>32</Id>
      <Name>ybhwnjxjwavjpwbkr</Name>
      <Duration>2.613411881315248</Duration>
    </Song>
    <Song>
      <Id>33</Id>
      <Name>rcnrfhakwhbos</Name>
      <Duration>1.6309821394416422</Duration>
    </Song>
    <Song>
      <Id>34</Id>
      <Name>evgceumwuislvrn</Name>
      <Duration>1.985716919408048</Duration>
    </Song>
    <Song>
      <Id>35</Id>
      <Name>avnorfinmp</Name>
      <Duration>4.2699077661474734</Duration>
    </Song>
    <Song>
      <Id>36</Id>
      <Name>kgnfvemdwppvvnon</Name>
      <Duration>1.7451252805744881</Duration>
    </Song>
    <Song>
      <Id>37</Id>
      <Name>ppetaoeasqivxnqheil</Name>
      <Duration>3.8952497397061672</Duration>
    </Song>
    <Song>
      <Id>38</Id>
      <Name>xcgwsuqtygvaqa</Name>
      <Duration>2.4933738687510481</Duration>
    </Song>
    <Song>
      <Id>39</Id>
      <Name>qretlnsrhfgjfs</Name>
      <Duration>1.0687705609336358</Duration>
    </Song>
    <Song>
      <Id>40</Id>
      <Name>rbmdujiyrby</Name>
      <Duration>4.9036673348879756</Duration>
    </Song>
    <Song>
      <Id>41</Id>
      <Name>brutysrlomekokjs</Name>
      <Duration>3.8158679156638069</Duration>
    </Song>
    <Song>
      <Id>42</Id>
      <Name>mieyiuiuttmsujofrkx</Name>
      <Duration>1.3390735687404283</Duration>
    </Song>
    <Song>
      <Id>43</Id>
      <Name>fmyyktxpxnexjg</Name>
      <Duration>4.7056356718324288</Duration>
    </Song>
    <Song>
      <Id>44</Id>
      <Name>yqwxrbsiayfrio</Name>
      <Duration>4.6195501743906879</Duration>
    </Song>
    <Song>
      <Id>45</Id>
      <Name>drajknveux</Name>
      <Duration>3.8911636536434124</Duration>
    </Song>
    <Song>
      <Id>46</Id>
      <Name>ijyxyjkmmk</Name>
      <Duration>1.6259745292486505</Duration>
    </Song>
    <Song>
      <Id>47</Id>
      <Name>tswpykhhcdrcn</Name>
      <Duration>1.0361090600658716</Duration>
    </Song>
    <Song>
      <Id>48</Id>
      <Name>vcelaqurkojeoqgts</Name>
      <Duration>1.7508538997503249</Duration>
    </Song>
    <Song>
      <Id>49</Id>
      <Name>gfyeorffhul</Name>
      <Duration>2.3880487039629594</Duration>
    </Song>
    <Song>
      <Id>50</Id>
      <Name>qibeidweekbcslvxi</Name>
      <Duration>2.3840500583797928</Duration>
    </Song>
    <Song>
      <Id>51</Id>
      <Name>nqdyvilpkoccuvaxro</Name>
      <Duration>3.6297935473871386</Duration>
    </Song>
    <Song>
      <Id>52</Id>
      <Name>baoclxsiimav</Name>
      <Duration>2.185544720937286</Duration>
    </Song>
    <Song>
      <Id>53</Id>
      <Name>ebhyqgtphxhvlxfsssp</Name>
      <Duration>2.6369894052096594</Duration>
    </Song>
    <Song>
      <Id>54</Id>
      <Name>wkjsgcccghqasph</Name>
      <Duration>4.9687363896373364</Duration>
    </Song>
    <Song>
      <Id>55</Id>
      <Name>hkhedcgkdsgcvriqevo</Name>
      <Duration>4.0116076511384957</Duration>
    </Song>
    <Song>
      <Id>56</Id>
      <Name>meraeleolytqefgr</Name>
      <Duration>2.3057088513419539</Duration>
    </Song>
    <Song>
      <Id>57</Id>
      <Name>vxjudlyqclkday</Name>
      <Duration>3.8902957192111276</Duration>
    </Song>
    <Song>
      <Id>58</Id>
      <Name>ldwufnghie</Name>
      <Duration>3.1177002895240209</Duration>
    </Song>
    <Song>
      <Id>59</Id>
      <Name>lphmesdjonftb</Name>
      <Duration>1.055335178997058</Duration>
    </Song>
    <Song>
      <Id>60</Id>
      <Name>sroidfdkppjcmuglnr</Name>
      <Duration>4.8112741461076185</Duration>
    </Song>
    <Song>
      <Id>61</Id>
      <Name>ntvsswoqaekfmomwtf</Name>
      <Duration>1.4690503624589417</Duration>
    </Song>
    <Song>
      <Id>62</Id>
      <Name>vnibvthsgjdgxfwsok</Name>
      <Duration>2.5470034654936771</Duration>
    </Song>
    <Song>
      <Id>63</Id>
      <Name>olywafsotlsiyqgnr</Name>
      <Duration>4.1394880787187667</Duration>
    </Song>
    <Song>
      <Id>64</Id>
      <Name>xtthynioeeuw</Name>
      <Duration>4.12985337904182</Duration>
    </Song>
    <Song>
      <Id>65</Id>
      <Name>cjdunnelwkwy</Name>
      <Duration>3.6551032437268196</Duration>
    </Song>
    <Song>
      <Id>66</Id>
      <Name>wnegutqrxmv</Name>
      <Duration>1.3882625901085617</Duration>
    </Song>
    <Song>
      <Id>67</Id>
      <Name>qukvkdenbossivw</Name>
      <Duration>1.5757424643150264</Duration>
    </Song>
    <Song>
      <Id>68</Id>
      <Name>xyhgsqhlkrfiqjtvgo</Name>
      <Duration>2.1070030131875552</Duration>
    </Song>
    <Song>
      <Id>69</Id>
      <Name>maimonbluuv</Name>
      <Duration>4.0479143448397119</Duration>
    </Song>
    <Song>
      <Id>70</Id>
      <Name>jhjctnxrmirx</Name>
      <Duration>2.9613136374211466</Duration>
    </Song>
    <Song>
      <Id>71</Id>
      <Name>oholrkyxtdcgyp</Name>
      <Duration>4.3450210291636271</Duration>
    </Song>
    <Song>
      <Id>72</Id>
      <Name>pejnwmroetnytq</Name>
      <Duration>1.1077396516258546</Duration>
    </Song>
    <Song>
      <Id>73</Id>
      <Name>fmhkitkjpx</Name>
      <Duration>3.3049452082742681</Duration>
    </Song>
    <Song>
      <Id>74</Id>
      <Name>cpygheowruvwnpkxymw</Name>
      <Duration>1.9746578708173046</Duration>
    </Song>
    <Song>
      <Id>75</Id>
      <Name>jbygjxegnbgfrx</Name>
      <Duration>4.5050827877154029</Duration>
    </Song>
    <Song>
      <Id>76</Id>
      <Name>bndmqknueykpl</Name>
      <Duration>4.1707585547914539</Duration>
    </Song>
    <Song>
      <Id>77</Id>
      <Name>qfxgatprlhuqhxmymdv</Name>
      <Duration>3.8536687613714804</Duration>
    </Song>
    <Song>
      <Id>78</Id>
      <Name>rpllfxtqbhcgbrbfigw</Name>
      <Duration>2.0455491459209236</Duration>
    </Song>
    <Song>
      <Id>79</Id>
      <Name>pvngmldixodsm</Name>
      <Duration>2.8058656127219392</Duration>
    </Song>
    <Song>
      <Id>80</Id>
      <Name>oqxtgnobvtwgtoq</Name>
      <Duration>2.8889045179304222</Duration>
    </Song>
    <Song>
      <Id>81</Id>
      <Name>aoxxlinrimcif</Name>
      <Duration>3.4238522129244413</Duration>
    </Song>
    <Song>
      <Id>82</Id>
      <Name>qglgdbhljrnvniwru</Name>
      <Duration>1.2773241280938146</Duration>
    </Song>
    <Song>
      <Id>83</Id>
      <Name>qpepgnebxnoe</Name>
      <Duration>4.0402460275405305</Duration>
    </Song>
    <Song>
      <Id>84</Id>
      <Name>kypfxhlottqdapkmblf</Name>
      <Duration>1.0172145650802249</Duration>
    </Song>
    <Song>
      <Id>85</Id>
      <Name>vaowgnucia</Name>
      <Duration>3.4058803605874441</Duration>
    </Song>
    <Song>
      <Id>86</Id>
      <Name>rfxhxebkuojekm</Name>
      <Duration>1.5355496725698699</Duration>
    </Song>
    <Song>
      <Id>87</Id>
      <Name>pxwicppbaxsqkqppd</Name>
      <Duration>3.2847989435702556</Duration>
    </Song>
    <Song>
      <Id>88</Id>
      <Name>dhwypakerua</Name>
      <Duration>4.5770807362054846</Duration>
    </Song>
    <Song>
      <Id>89</Id>
      <Name>komcpohgwghtjxto</Name>
      <Duration>2.7789885656810314</Duration>
    </Song>
    <Song>
      <Id>90</Id>
      <Name>koiaxsbekjfwybtgb</Name>
      <Duration>1.030318389660827</Duration>
    </Song>
  </Playlist>
  <OwnerId>0</OwnerId>
</PlayList>